.reuse/dep5
AUTHORS.md
CHANGELOG.md
CITATION.cff
CODE_OF_CONDUCT.md
CONTRIBUTING.md
LICENSE
README.md
codemeta.json
mkdocs.yml
dirschema/__init__.py
dirschema/adapters.py
dirschema/cli.py
dirschema/core.py
dirschema/json/__init__.py
dirschema/json/handler.py
dirschema/json/handler_pydantic.py
dirschema/json/handlers.py
dirschema/json/parse.py
dirschema/json/validate.py
dirschema/log.py
dirschema/validate.py
dirschema-0.1.0.dist-info/LICENSE
dirschema-0.1.0.dist-info/LICENSES/CC0-1.0.txt
dirschema-0.1.0.dist-info/LICENSES/MIT.txt
dirschema-0.1.0.dist-info/METADATA
dirschema-0.1.0.dist-info/WHEEL
dirschema-0.1.0.dist-info/entry_points.txt
dirschema-0.1.0.dist-info/RECORD
