Metadata-Version: 2.1
Name: dirschema
Version: 0.1.0
Summary: Spec and validator for directories, files and metadata based on JSON Schema and regexes.
Home-page: https://materials-data-science-and-informatics.github.io/dirschema
License: MIT
Keywords: jsonschema,validation,directory,structure,fair,metadata
Author: Anton Pirogov
Author-email: a.pirogov@fz-juelich.de
Requires-Python: >=3.8,<3.11
Classifier: Development Status :: 3 - Alpha
Classifier: Environment :: Console
Classifier: Intended Audience :: Developers
Classifier: Intended Audience :: Science/Research
Classifier: License :: OSI Approved :: MIT License
Classifier: Operating System :: OS Independent
Classifier: Programming Language :: Python :: 3
Classifier: Programming Language :: Python :: 3.8
Classifier: Programming Language :: Python :: 3.9
Classifier: Programming Language :: Python :: 3.10
Classifier: Topic :: Scientific/Engineering
Classifier: Topic :: Software Development
Classifier: Typing :: Typed
Provides-Extra: h5
Requires-Dist: entrypoints (>=0.4,<0.5)
Requires-Dist: h5py (>=3.4.0,<4.0.0) ; extra == "h5"
Requires-Dist: jsonref (>=0.2,<0.3)
Requires-Dist: jsonschema (>=4.4.0,<5.0.0)
Requires-Dist: numpy (>=1.21.2,<2.0.0) ; extra == "h5"
Requires-Dist: pydantic (>=1.8.2,<2.0.0)
Requires-Dist: ruamel.yaml (>=0.17.16,<0.18.0)
Requires-Dist: typer (>=0.9.0,<0.10.0)
Requires-Dist: typing-extensions (>=4.5.0,<5.0.0)
Project-URL: Documentation, https://materials-data-science-and-informatics.github.io/dirschema
Project-URL: Repository, https://github.com/Materials-Data-Science-and-Informatics/dirschema
